procpath/__init__.py
procpath/__main__.py
procpath/cli.py
procpath/playbook.py
procpath/plotting.py
procpath/procfile.py
procpath/procrec.py
procpath/procret.py
procpath/proctree.py
procpath/sqliteviz.py
procpath/treefarm.py
procpath/utility.py
procpath/cmd/__init__.py
procpath/cmd/explore.py
procpath/cmd/play.py
procpath/cmd/plot.py
procpath/cmd/query.py
procpath/cmd/record.py
procpath/cmd/watch.py
procpath/test/__init__.py
procpath/test/cmd.py
procpath/test/unit.py
Procpath-1.14.0.dist-info/METADATA
Procpath-1.14.0.dist-info/WHEEL
Procpath-1.14.0.dist-info/entry_points.txt
Procpath-1.14.0.dist-info/top_level.txt
Procpath-1.14.0.dist-info/RECORD
