Metadata-Version: 2.1
Name: Procpath
Version: 1.14.0
Summary: Procpath is a process tree analysis workbench
Home-page: https://heptapod.host/saajns/procpath
Author: saaj
Author-email: mail@saaj.me
License: LGPL-3.0-only
Project-URL: Source Code, https://heptapod.host/saajns/procpath
Project-URL: Documentation, https://saajns.heptapod.io/procpath/
Project-URL: Release Notes, https://saajns.heptapod.io/procpath/history.html
Keywords: procfs jsonpath sqlite plotting
Classifier: Environment :: Console
Classifier: Operating System :: POSIX :: Linux
Classifier: Topic :: System :: Monitoring
Classifier: Topic :: Software Development :: Libraries
Classifier: Programming Language :: Python :: 3
Classifier: Programming Language :: Python :: 3 :: Only
Classifier: Programming Language :: Python :: 3.9
Classifier: Programming Language :: Python :: 3.10
Classifier: Programming Language :: Python :: 3.11
Classifier: Programming Language :: Python :: 3.12
Classifier: Programming Language :: Python :: 3.13
Classifier: Programming Language :: Python :: Implementation :: CPython
Classifier: Programming Language :: Python :: Implementation :: PyPy
Classifier: Intended Audience :: Developers
Classifier: Intended Audience :: System Administrators
Requires-Python: >= 3.9
Requires-Dist: jsonpyth<0.2,>=0.1.3
Requires-Dist: pygal<4,>=3.0.4
